[
    {
        "title": "CRNN for licence plates OCR",
        "description": "Characters recognition from license plates using convolutional recurrent neural networks.",
        "tags": ["Python", "Keras", "Numpy", "CRNN"],
        "thumbnail": "https://cdn.discordapp.com/attachments/874390691931902022/878748098879434782/ocr.png",
        "link": "post1"
    },
    {
        "title": "Deep learning for image classification",
        "description": "Deep learning for image classification using Keras and Tensorflow.",
        "tags": ["Python", "Keras", "Tensorflow", "Image"],
        "thumbnail": "https://github.com/Arksyd96/ocr-license-plates-crnn/blob/master/text-from-image-ocr.ipynb",
        "link": "deep_learning_for_image_classification"
    },
    {
        "title": "Bases en probabilités pour du Machine learning",
        "description": "Mes notes sur les différents sujets de probabilités utils pour faire du Machine learning (Variables aléatoire,  Fonctions de distribution, Chaîne de Markov)",
        "tags": ["Probabilities", "Machine learning"],
        "thumbnail": "https://github.com/Arksyd96/ocr-license-plates-crnn/blob/master/text-from-image-ocr.ipynb",
        "link": "mes_notes_en_probabilites"
    }
]